{
  "categories": [
    {
      "name": "Things You Can Hear",
      "words": [
        "ECHO",
        "WHISTLE",
        "THUNDER",
        "ALARM"
      ],
      "difficulty": "yellow"
    },
    {
      "name": "Words That Can Mean Both a Person and a Thing",
      "words": [
        "DRIVER",
        "ANCHOR",
        "PILOT",
        "AGENT"
      ],
      "difficulty": "green"
    },
    {
      "name": "Actions You Can Do With Your Hands",
      "words": [
        "CLAP",
        "SCRATCH",
        "POINT",
        "SNAP"
      ],
      "difficulty": "blue"
    },
    {
      "name": "Concepts Related to Control and Influence",
      "words": [
        "POWER",
        "LEVERAGE",
        "AUTHORITY",
        "COMMAND"
      ],
      "difficulty": "purple"
    }
  ],
  "date": null,
  "decoys": [
    {
      "category_a": "Words That Can Mean Both a Person and a Thing",
      "category_b": "Concepts Related to Control and Influence",
      "word": "Anchor"
    },
    {
      "category_a": "Words That Can Mean Both a Person and a Thing",
      "category_b": "Concepts Related to Control and Influence",
      "word": "Pilot"
    },
    {
      "category_a": "Words That Can Mean Both a Person and a Thing",
      "category_b": "Concepts Related to Control and Influence",
      "word": "Driver"
    }
  ],
  "design_notes": "",
  "id": null,
  "language": "en",
  "other_trick": "‘Alarm’ and ‘Whistle’ can be both sounds (Things You Can Hear) and signals of control or warnings (Concepts Related to Control and Influence).",
  "_validation": {
    "valid": true,
    "errors": [],
    "duplicate_words": []
  }
}