{
  "categories": [
    {
      "name": "Types of sports competitions",
      "words": [
        "MATCH",
        "BOUT",
        "MEET",
        "RALLY"
      ],
      "difficulty": "yellow"
    },
    {
      "name": "Things you keep a record in",
      "words": [
        "DIARY",
        "JOURNAL",
        "LOG",
        "LEDGER"
      ],
      "difficulty": "green"
    },
    {
      "name": "Ways to start a fire",
      "words": [
        "KINDLE",
        "SPARK",
        "IGNITE",
        "TORCH"
      ],
      "difficulty": "blue"
    },
    {
      "name": "Classic 90s sitcoms",
      "words": [
        "FRIENDS",
        "SEINFELD",
        "CHEERS",
        "FRASIER"
      ],
      "difficulty": "purple"
    }
  ],
  "decoys": [
    {
      "category_a": "Types of sports competitions",
      "category_b": "Ways to start a fire",
      "reason_a": "A tennis match or boxing match is a type of sporting event",
      "reason_b": "A match is a common tool used to light fires",
      "word": "MATCH"
    },
    {
      "category_a": "Things you keep a record in",
      "category_b": "Ways to start a fire",
      "reason_a": "A log is a written record of events like a ship's log",
      "reason_b": "A log is a piece of wood you burn in a fireplace",
      "word": "LOG"
    }
  ],
  "other_trick": "RALLY tempts toward other meanings like a political rally or to rally support, TORCH can mean the verb to set fire to something, and SPARK can mean to trigger an idea or romance.",
  "thinking": {
    "all_16_words": "MATCH BOUT MEET RALLY DIARY JOURNAL LOG LEDGER KINDLE SPARK IGNITE TORCH FRIENDS SEINFELD CHEERS FRASIER",
    "anchors": [
      {
        "home_category": "Types of sports competitions",
        "meaning_a": "tennis match, boxing match, wrestling match",
        "meaning_b": "fire-starting stick",
        "tempts_toward": "Things that create fire",
        "word": "MATCH"
      },
      {
        "home_category": "Types of sports competitions",
        "meaning_a": "hockey stick, lacrosse stick, walking stick",
        "meaning_b": "wooden branch",
        "tempts_toward": "Things that create fire",
        "word": "STICK"
      },
      {
        "home_category": "Things you keep a record in",
        "meaning_a": "ship's log, captain's log",
        "meaning_b": "piece of wood for burning",
        "tempts_toward": "Things that create fire",
        "word": "LOG"
      }
    ]
  },
  "language": "en",
  "_validation": {
    "valid": true,
    "errors": [],
    "duplicate_words": []
  }
}